libbackground/__init__.py
libbackground/__init__.pyi
libbackground/libbackground.cpython-310-x86_64-linux-gnu.so
swgo_bali.libs/libgcc_s-0cd532bd.so.1
swgo_bali.libs/libstdc++-5d72f927.so.6.0.33
swgo_bali-0.2.0.dist-info/METADATA
swgo_bali-0.2.0.dist-info/WHEEL
swgo_bali-0.2.0.dist-info/RECORD
swgo_bali-0.2.0.dist-info/licenses/LICENSE
swgo_bali-0.2.0.dist-info/sboms/auditwheel.cdx.json
