Metadata-Version: 2.4
Name: swgo-bali
Version: 0.2.0
Summary: Python bindings for the SWGO Background Library
Author-Email: Johannes Bennemann <johannes.bennemann@mpi-hd.mpg.de>
Maintainer-Email: Johannes Bennemann <johannes.bennemann@mpi-hd.mpg.de>
License-Expression: MPL-2.0
License-File: LICENSE
Classifier: Development Status :: 4 - Beta
Classifier: Programming Language :: Python :: 3 :: Only
Classifier: Programming Language :: Python :: 3.9
Classifier: Programming Language :: Python :: 3.10
Classifier: Programming Language :: Python :: 3.11
Classifier: Programming Language :: Python :: 3.12
Classifier: Programming Language :: Python :: 3.13
Classifier: Programming Language :: C++
Classifier: Topic :: Scientific/Engineering :: Physics
Classifier: Operating System :: POSIX :: Linux
Project-URL: Homepage, https://gitlab.com/swgo-collaboration/swgo-background-library
Project-URL: Documentation, https://swgo-background-library-6e5922.gitlab.io/
Requires-Python: >=3.9
Requires-Dist: typing_extensions
